weather_mcp/__init__.py
weather_mcp/main.py
weather_mcp/server.py
tc_weather_mcp_server-1.0.1.dist-info/METADATA
tc_weather_mcp_server-1.0.1.dist-info/WHEEL
tc_weather_mcp_server-1.0.1.dist-info/entry_points.txt
tc_weather_mcp_server-1.0.1.dist-info/top_level.txt
tc_weather_mcp_server-1.0.1.dist-info/RECORD
