Metadata-Version: 2.4
Name: tc-weather-mcp-server
Version: 1.0.1
Summary: Weather MCP Server with National Weather Service API integration
Author-email: Anirudh <anirudhudugani@gmail.com>
License: MIT
Project-URL: Homepage, https://github.com/Aniirudh/tc-weather-mcp-server
Project-URL: Repository, https://github.com/Aniirudh/tc-weather-mcp-server
Project-URL: Issues, https://github.com/Aniirudh/tc-weather-mcp-server/issues
Project-URL: Documentation, https://github.com/Aniirudh/tc-weather-mcp-server#readme
Keywords: mcp,weather,api,server,claude
Classifier: Development Status :: 4 - Beta
Classifier: Intended Audience :: Developers
Classifier: License :: OSI Approved :: MIT License
Classifier: Programming Language :: Python :: 3
Classifier: Programming Language :: Python :: 3.8
Classifier: Programming Language :: Python :: 3.9
Classifier: Programming Language :: Python :: 3.10
Classifier: Programming Language :: Python :: 3.11
Classifier: Programming Language :: Python :: 3.12
Requires-Python: >=3.8
Requires-Dist: mcp>=1.0.0
Requires-Dist: httpx>=0.24.0
Requires-Dist: fastmcp>=0.1.0
Provides-Extra: dev
Requires-Dist: pytest>=7.0.0; extra == "dev"
Requires-Dist: pytest-asyncio>=0.21.0; extra == "dev"
Requires-Dist: black>=23.0.0; extra == "dev"
Requires-Dist: flake8>=6.0.0; extra == "dev"
Requires-Dist: mypy>=1.0.0; extra == "dev"
